backwardcompatibilityml/__init__.py
backwardcompatibilityml/comparison_management.py
backwardcompatibilityml/metrics.py
backwardcompatibilityml/scores.py
backwardcompatibilityml/sweep_management.py
backwardcompatibilityml/helpers/__init__.py
backwardcompatibilityml/helpers/comparison.py
backwardcompatibilityml/helpers/http.py
backwardcompatibilityml/helpers/models.py
backwardcompatibilityml/helpers/training.py
backwardcompatibilityml/helpers/utils.py
backwardcompatibilityml/loss/__init__.py
backwardcompatibilityml/loss/new_error.py
backwardcompatibilityml/loss/strict_imitation.py
backwardcompatibilityml/tensorflow/__init__.py
backwardcompatibilityml/tensorflow/helpers.py
backwardcompatibilityml/tensorflow/models.py
backwardcompatibilityml/tensorflow/loss/__init__.py
backwardcompatibilityml/tensorflow/loss/new_error.py
backwardcompatibilityml/tensorflow/loss/strict_imitation.py
backwardcompatibilityml/widgets/__init__.py
backwardcompatibilityml/widgets/compatibility_analysis/__init__.py
backwardcompatibilityml/widgets/compatibility_analysis/compatibility_analysis.py
backwardcompatibilityml/widgets/compatibility_analysis/resources/__init__.py
backwardcompatibilityml/widgets/compatibility_analysis/resources/widget-build.js
backwardcompatibilityml/widgets/compatibility_analysis/resources/widget.css
backwardcompatibilityml/widgets/compatibility_analysis/resources/widget.html
backwardcompatibilityml/widgets/model_comparison/__init__.py
backwardcompatibilityml/widgets/model_comparison/model_comparison.py
backwardcompatibilityml/widgets/model_comparison/resources/__init__.py
backwardcompatibilityml/widgets/model_comparison/resources/widget-build.js
backwardcompatibilityml/widgets/model_comparison/resources/widget.css
backwardcompatibilityml/widgets/model_comparison/resources/widget.html
backwardcompatibilityml-1.4.2.dist-info/LICENSE.txt
backwardcompatibilityml-1.4.2.dist-info/METADATA
backwardcompatibilityml-1.4.2.dist-info/WHEEL
backwardcompatibilityml-1.4.2.dist-info/top_level.txt
backwardcompatibilityml-1.4.2.dist-info/RECORD
