Metadata-Version: 2.1
Name: backwardcompatibilityml
Version: 1.4.2
Summary: Project for open sourcing research efforts on Backward Compatibility in Machine Learning
Home-page: https://github.com/microsoft/BackwardCompatibilityML
Author: Besmira Nushi
Author-email: benushi@microsoft.com
License: UNKNOWN
Platform: UNKNOWN
Classifier: Programming Language :: Python :: 3
Classifier: License :: OSI Approved :: MIT License
Classifier: Operating System :: OS Independent
Requires-Dist: torch (==1.5.1)
Requires-Dist: Jinja2 (==2.11.2)
Requires-Dist: numpy (==1.19.3)
Requires-Dist: scikit-learn (==0.23.1)
Requires-Dist: rai-core-flask (==0.0.2)
Requires-Dist: tensorboard (==2.4.0)
Requires-Dist: tensorboard-plugin-wit (==1.7.0)
Requires-Dist: tensorflow (==2.4.0)
Requires-Dist: tensorflow-datasets (==4.1.0)
Requires-Dist: tensorflow-estimator (==2.4.0)
Requires-Dist: tensorflow-metadata (==0.25.0)
Requires-Dist: Pillow (==7.2.0)
Requires-Dist: mlflow (==1.12.1)
Requires-Dist: greenlet (==0.4.16)
Provides-Extra: dev
Requires-Dist: sphinx (==3.2.1) ; extra == 'dev'
Requires-Dist: recommonmark (==0.6.0) ; extra == 'dev'
Requires-Dist: sphinx-rtd-theme (==0.5.0) ; extra == 'dev'
